pycounts_ks/__init__.py
pycounts_ks/plotting.py
pycounts_ks/pycounts_ks.py
pycounts_ks-0.1.0.dist-info/LICENSE
pycounts_ks-0.1.0.dist-info/METADATA
pycounts_ks-0.1.0.dist-info/WHEEL
pycounts_ks-0.1.0.dist-info/RECORD
